rrule/__init__.py
rrule/rrule.cpython-311-darwin.so
rrule_fork-0.0.2.dist-info/METADATA
rrule_fork-0.0.2.dist-info/WHEEL
rrule_fork-0.0.2.dist-info/RECORD
